usabilla.py
usabilla_api-2.0.4.dist-info/LICENSE.MD
usabilla_api-2.0.4.dist-info/METADATA
usabilla_api-2.0.4.dist-info/WHEEL
usabilla_api-2.0.4.dist-info/top_level.txt
usabilla_api-2.0.4.dist-info/RECORD
