Metadata-Version: 2.1
Name: usabilla-api
Version: 2.0.4
Summary: Python client for Usabilla API
Home-page: https://github.com/usabilla/api-python
Download-URL: https://github.com/usabilla/api-python/tarball/2.0.4
Author: Usabilla
Author-email: development@usabilla.com
License: MIT
License-File: LICENSE.MD
Requires-Dist: requests
